dff/module.v
/*
MIT License

Copyright (c) 2021 Ashwin-Rajesh

Permission is hereby granted, free of charge, to any person obtaining a copy
of this software and associated documentation files (the "Software"), to deal
in the Software without restriction, including without limitation the rights
to use, copy, modify, merge, publish, distribute, sublicense, and/or sell
copies of the Software, and to permit persons to whom the Software is
furnished to do so, subject to the following conditions:

The above copyright notice and this permission notice shall be included in all
copies or substantial portions of the Software.

THE SOFTWARE IS PROVIDED "AS IS", WITHOUT WARRANTY OF ANY KIND, EXPRESS OR
IMPLIED, INCLUDING BUT NOT LIMITED TO THE WARRANTIES OF MERCHANTABILITY,
FITNESS FOR A PARTICULAR PURPOSE AND NONINFRINGEMENT. IN NO EVENT SHALL THE
AUTHORS OR COPYRIGHT HOLDERS BE LIABLE FOR ANY CLAIM, DAMAGES OR OTHER
LIABILITY, WHETHER IN AN ACTION OF CONTRACT, TORT OR OTHERWISE, ARISING FROM,
OUT OF OR IN CONNECTION WITH THE SOFTWARE OR THE USE OR OTHER DEALINGS IN THE
SOFTWARE.
*/

module dff(
    input d,
    input clk,
    input rst,

    output reg q = 0
);

    always @rst q <= 0;

    always @(posedge clk) begin
        q <= d;
    end

`ifdef COCOTB_SIM
    initial begin
        $dumpfile ("waveform.vcd");
        $dumpvars (0, dff);
        #1;
    end
`endif

endmodule

dff/waveform.vcd
$date
	Thu Oct  7 09:47:05 2021
$end
$version
	Icarus Verilog
$end
$timescale
	1ps
$end
$scope module dff $end
$var wire 1 ! clk $end
$var wire 1 " d $end
$var wire 1 # rst $end
$var reg 1 $ q $end
$upscope $end
$enddefinitions $end
#0
$dumpvars
0$
z#
1"
0!
$end
#5000000
1$
1!
#10000000
0!
#15000000
0"
1!
#20000000
0!
#25000000
0$
1!
#30000000
0!
#35000000
1!
#40000000
0!
#45000000
1!
#50000000
0!
#55000000
1!
#60000000
0!
#65000000
1"
1!
#70000000
0!
#75000000
1$
1!
#80000000
0!
#85000000
0"
1!
#90000000
0!
#95000000
0$
1!
#100000000
0!
#105000000
1!
#110000000
0!
#115000000
1"
1!
#120000000
0!
#125000000
1$
1!
#130000000
0!
#135000000
1!
#140000000
0!
#145000000
1!
#150000000
0!
#155000000
1!
#160000000
0!
#165000000
0"
1!
#170000000
0!
#175000000
0$
1!
#180000000
0!
#185000000
1!
#190000000
0!
#195000000
1!
#200000000
0!
#205000000
1!
#210000000
0!
#215000000
1"
1!
#220000000
0!
#225000000
1$
1!
#230000000
0!
#235000000
0"
1!
#240000000
0!
#245000000
1"
0$
1!
#250000000
0!
#255000000
0"
1$
1!
#260000000
0!
#265000000
0$
1!
#270000000
0!
#275000000
1"
1!
#280000000
0!
#285000000
0"
1$
1!
#290000000
0!
#295000000
0$
1!
#300000000
0!
#305000000
1!
#310000000
0!
#315000000
1!
#320000000
0!
#325000000
1!
#330000000
0!
#335000000
1"
1!
#340000000
0!
#345000000
1$
1!
#350000000
0!
#355000000
1!
#360000000
0!
#365000000
0"
1!
#370000000
0!
#375000000
1"
0$
1!
#380000000
0!
#385000000
1$
1!
#390000000
0!
#395000000
1!
#400000000
0!
#405000000
1!
#410000000
0!
#415000000
1!
#420000000
0!
#425000000
0"
1!
#430000000
0!
#435000000
0$
1!
#440000000
0!
#445000000
1!
#450000000
0!
#455000000
1"
1!
#460000000
0!
#465000000
1$
1!
#470000000
0!
#475000000
0"
1!
#480000000
0!
#485000000
1"
0$
1!
#490000000
0!
#495000000
1$
1!
#500000000
0!
#505000000
1!
#510000000
0!
#515000000
1!
#520000000
0!
#525000000
0"
1!
#530000000
0!
#535000000
0$
1!
#540000000
0!
#545000000
1!
#550000000
0!
#555000000
1!
#560000000
0!
#565000000
1"
1!
#570000000
0!
#575000000
1$
1!
#580000000
0!
#585000000
1!
#590000000
0!
#595000000
1!
#600000000
0!
#605000000
1!
#610000000
0!
#615000000
0"
1!
#620000000
0!
#625000000
0$
1!
#630000000
0!
#635000000
1!
#640000000
0!
#645000000
1!
#650000000
0!
#655000000
1!
#660000000
0!
#665000000
1"
1!
#670000000
0!
#675000000
1$
1!
#680000000
0!
#685000000
0"
1!
#690000000
0!
#695000000
0$
1!
#700000000
0!
#705000000
1!
#710000000
0!
#715000000
1"
1!
#720000000
0!
#725000000
1$
1!
#730000000
0!
#735000000
1!
#740000000
0!
#745000000
1!
#750000000
0!
#755000000
1!
#760000000
0!
#765000000
0"
1!
#770000000
0!
#775000000
0$
1!
#780000000
0!
#785000000
1!
#790000000
0!
#795000000
1"
1!
#800000000
0!
#805000000
0"
1$
1!
#810000000
0!
#815000000
0$
1!
#820000000
0!
#825000000
1!
#830000000
0!
#835000000
1!
#840000000
0!
#845000000
1!
#850000000
0!
#855000000
1"
1!
#860000000
0!
#865000000
0"
1$
1!
#870000000
0!
#875000000
1"
0$
1!
#880000000
0!
#885000000
1$
1!
#890000000
0!
#895000000
1!
#900000000
0!
#905000000
1!
#910000000
0!
#915000000
1!
#920000000
0!
#925000000
0"
1!
#930000000
0!
#935000000
1"
0$
1!
#940000000
0!
#945000000
0"
1$
1!
#950000000
0!
#955000000
0$
1!
#960000000
0!
#965000000
1!
#970000000
0!
#975000000
1!
#980000000
0!
#985000000
1"
1!
#990000000
0!
#995000000
1$
1!
#1000000000
0!
#1005000000
1!
#1010000000
0!
#1015000000
1!
#1020000000
0!
#1025000000
0"
1!
#1030000000
0!
#1035000000
0$
1!
#1040000000
0!
#1045000000
1!
#1050000000
0!
#1055000000
1!
#1060000000
0!
#1065000000
1"
1!
#1070000000
0!
#1075000000
1$
1!
#1080000000
0!
#1085000000
1!
#1090000000
0!
#1095000000
0"
1!
#1100000000
0!
#1105000000
0$
1!
#1110000000
0!
#1115000000
1!
#1120000000
0!
#1125000000
1"
1!
#1130000000
0!
#1135000000
1$
1!
#1140000000
0!
#1145000000
1!
#1150000000
0!
#1155000000
0"
1!
#1160000000
0!
#1165000000
1"
0$
1!
#1170000000
0!
#1175000000
1$
1!
#1180000000
0!
#1185000000
0"
1!
#1190000000
0!
#1195000000
0$
1!
#1200000000
0!
#1205000000
1!
#1210000000
0!
#1215000000
1!
#1220000000
0!
#1225000000
1!
#1230000000
0!
#1235000000
1"
1!
#1240000000
0!
#1245000000
0"
1$
1!
#1250000000
0!
#1255000000
0$
1!
#1260000000
0!
#1265000000
1!
#1270000000
0!
#1275000000
1!
#1280000000
0!
#1285000000
1!
#1290000000
0!
#1295000000
1"
1!
#1300000000
0!
#1305000000
0"
1$
1!
#1310000000
0!
#1315000000
0$
1!
#1320000000
0!
#1325000000
1!
#1330000000
0!
#1335000000
1!
#1340000000
0!
#1345000000
1"
1!
#1350000000
0!
#1355000000
1$
1!
#1360000000
0!
#1365000000
1!
#1370000000
0!
#1375000000
1!
#1380000000
0!
#1385000000
0"
1!
#1390000000
0!
#1395000000
0$
1!
#1400000000
0!
#1405000000
1"
1!
#1410000000
0!
#1415000000
0"
1$
1!
#1420000000
0!
#1425000000
0$
1!
#1430000000
0!
#1435000000
1"
1!
#1440000000
0!
#1445000000
1$
1!
#1450000000
0!
#1455000000
1!
#1460000000
0!
#1465000000
1!
#1470000000
0!
#1475000000
1!
#1480000000
0!
#1485000000
0"
1!
#1490000000
0!
#1495000000
1"
0$
1!
#1500000000
0!
#1505000000
1$
1!
#1510000000
0!
#1515000000
1!
#1520000000
0!
#1525000000
1!
#1530000000
0!
#1535000000
1!
#1540000000
0!
#1545000000
0"
1!
#1550000000
0!
#1555000000
0$
1!
#1560000000
0!
#1565000000
1!
#1570000000
0!
#1575000000
1!
#1580000000
0!
#1585000000
1"
1!
#1590000000
0!
#1595000000
1$
1!
#1600000000
0!
#1605000000
1!
#1610000000
0!
#1615000000
1!
#1620000000
0!
#1625000000
0"
1!
#1630000000
0!
#1635000000
0$
1!
#1640000000
0!
#1645000000
1"
1!
#1650000000
0!
#1655000000
1$
1!
#1660000000
0!
#1665000000
1!
#1670000000
0!
#1675000000
0"
1!
#1680000000
0!
#1685000000
0$
1!
#1690000000
0!
#1695000000
1!
#1700000000
0!
#1705000000
1"
1!
#1710000000
0!
#1715000000
1$
1!
#1720000000
0!
#1725000000
1!
#1730000000
0!
#1735000000
1!
#1740000000
0!
#1745000000
1!
#1750000000
0!
#1755000000
0"
1!
#1760000000
0!
#1765000000
0$
1!
#1770000000
0!
#1775000000
1!
#1780000000
0!
#1785000000
1!
#1790000000
0!
#1795000000
1"
1!
#1800000000
0!
#1805000000
1$
1!
#1810000000
0!
#1815000000
1!
#1820000000
0!
#1825000000
0"
1!
#1830000000
0!
#1835000000
1"
0$
1!
#1840000000
0!
#1845000000
1$
1!
#1850000000
0!
#1855000000
1!
#1860000000
0!
#1865000000
1!
#1870000000
0!
#1875000000
0"
1!
#1880000000
0!
#1885000000
0$
1!
#1890000000
0!
#1895000000
1"
1!
#1900000000
0!
#1905000000
0"
1$
1!
#1910000000
0!
#1915000000
1"
0$
1!
#1920000000
0!
#1925000000
1$
1!
#1930000000
0!
#1935000000
1!
#1940000000
0!
#1945000000
1!
#1950000000
0!
#1955000000
0"
1!
#1960000000
0!
#1965000000
0$
1!
#1970000000
0!
#1975000000
1!
#1980000000
0!
#1985000000
1!
#1990000000
0!
#1995000000
1"
1!
#2000000000
0!
#2005000000
1$
1!
#2010000000
0!
#2015000000
1!
#2020000000
0!
#2025000000
1!
#2030000000
0!
#2035000000
1!
#2040000000
0!
#2045000000
0"
1!
#2050000000
0!
#2055000000
0$
1!
#2060000000
0!
#2065000000
1!
#2070000000
0!
#2075000000
1!
#2080000000
0!
#2085000000
1!
#2090000000
0!
#2095000000
1"
1!
#2100000000
0!
#2105000000
1$
1!
#2110000000
0!
#2115000000
0"
1!
#2120000000
0!
#2125000000
1"
0$
1!
#2130000000
0!
#2135000000
1$
1!
#2140000000
0!
#2145000000
1!
#2150000000
0!
#2155000000
0"
1!
#2160000000
0!
#2165000000
0$
1!
#2170000000
0!
#2175000000
1!
#2180000000
0!
#2185000000
1!
#2190000000
0!
#2195000000
1"
1!
#2200000000
0!
#2205000000
1$
1!
#2210000000
0!
#2215000000
1!
#2220000000
0!
#2225000000
1!
#2230000000
0!
#2235000000
0"
1!
#2240000000
0!
#2245000000
0$
1!
#2250000000
0!
#2255000000
1"
1!
#2260000000
0!
#2265000000
0"
1$
1!
#2270000000
0!
#2275000000
0$
1!
#2280000000
0!
#2285000000
1!
#2290000000
0!
#2295000000
1"
1!
#2300000000
0!
#2305000000
1$
1!
#2310000000
0!
#2315000000
1!
#2320000000
0!
#2325000000
1!
#2330000000
0!
#2335000000
0"
1!
#2340000000
0!
#2345000000
0$
1!
#2350000000
0!
#2355000000
1!
#2360000000
0!
#2365000000
1"
1!
#2370000000
0!
#2375000000
1$
1!
#2380000000
0!
#2385000000
0"
1!
#2390000000
0!
#2395000000
0$
1!
#2400000000
0!
#2405000000
1!
#2410000000
0!
#2415000000
1!
#2420000000
0!
#2425000000
1!
#2430000000
0!
#2435000000
1"
1!
#2440000000
0!
#2445000000
1$
1!
#2450000000
0!
#2455000000
1!
#2460000000
0!
#2465000000
0"
1!
#2470000000
0!
#2475000000
1"
0$
1!
#2480000000
0!
#2485000000
1$
1!
#2490000000
0!
#2495000000
1!
#2500000000
0!
#2505000000
1!
#2510000000
0!
#2515000000
1!
#2520000000
0!
#2525000000
0"
1!
#2530000000
0!
#2535000000
0$
1!
#2540000000
0!
#2545000000
1"
1!
#2550000000
0!
#2555000000
0"
1$
1!
#2560000000
0!
#2565000000
0$
1!
#2570000000
0!
#2575000000
1!
#2580000000
0!
#2585000000
1"
1!
#2590000000
0!
#2595000000
1$
1!
#2600000000
0!
#2605000000
1!
#2610000000
0!
#2615000000
1!
#2620000000
0!
#2625000000
0"
1!
#2630000000
0!
#2635000000
0$
1!
#2640000000
0!
#2645000000
1!
#2650000000
0!
#2655000000
1!
#2660000000
0!
#2665000000
1!
#2670000000
0!
#2675000000
1"
1!
#2680000000
0!
#2685000000
1$
1!
#2690000000
0!
#2695000000
0"
1!
#2700000000
0!
#2705000000
0$
1!
#2710000000
0!
#2715000000
1"
1!
#2720000000
0!
#2725000000
1$
1!
#2730000000
0!
#2735000000
1!
#2740000000
0!
#2745000000
0"
1!
#2750000000
0!
#2755000000
0$
1!
#2760000000
0!
#2765000000
1!
#2770000000
0!
#2775000000
1"
1!
#2780000000
0!
#2785000000
1$
1!
#2790000000
0!
#2795000000
1!
#2800000000
0!
#2805000000
1!
#2810000000
0!
#2815000000
1!
#2820000000
0!
#2825000000
0"
1!
#2830000000
0!
#2835000000
0$
1!
#2840000000
0!
#2845000000
1!
#2850000000
0!
#2855000000
1!
#2860000000
0!
#2865000000
1"
1!
#2870000000
0!
#2875000000
1$
1!
#2880000000
0!
#2885000000
1!
#2890000000
0!
#2895000000
1!
#2900000000
0!
#2905000000
0"
1!
#2910000000
0!
#2915000000
0$
1!
#2920000000
0!
#2925000000
1!
#2930000000
0!
#2935000000
1"
1!
#2940000000
0!
#2945000000
1$
1!
#2950000000
0!
#2955000000
1!
#2960000000
0!
#2965000000
1!
#2970000000
0!
#2975000000
1!
#2980000000
0!
#2985000000
0"
1!
#2990000000
0!
#2995000000
1"
0$
1!
#3000000000
0!
#3005000000
1$
1!
#3010000000
0!
#3015000000
1!
#3020000000
0!
#3025000000
1!
#3030000000
0!
#3035000000
1!
#3040000000
0!
#3045000000
0"
1!
#3050000000
0!
#3055000000
1"
0$
1!
#3060000000
0!
#3065000000
1$
1!
#3070000000
0!
#3075000000
1!
#3080000000
0!
#3085000000
0"
1!
#3090000000
0!
#3095000000
0$
1!
#3100000000
0!
#3105000000
1!
#3110000000
0!
#3115000000
1"
1!
#3120000000
0!
#3125000000
0"
1$
1!
#3130000000
0!
#3135000000
0$
1!
#3140000000
0!
#3145000000
1!
#3150000000
0!
#3155000000
1!
#3160000000
0!
#3165000000
1!
#3170000000
0!
#3175000000
1"
1!
#3180000000
0!
#3185000000
1$
1!
#3190000000
0!
#3195000000
1!
#3200000000
0!
#3205000000
1!
#3210000000
0!
#3215000000
1!
#3220000000
0!
#3225000000
0"
1!
#3230000000
0!
#3235000000
0$
1!
#3240000000
0!
#3245000000
1!
#3250000000
0!
#3255000000
1!
#3260000000
0!
#3265000000
1"
1!
#3270000000
0!
#3275000000
0"
1$
1!
#3280000000
0!
#3285000000
0$
1!
#3290000000
0!
#3295000000
1"
1!
#3300000000
0!
#3305000000
1$
1!
#3310000000
0!
#3315000000
0"
1!
#3320000000
0!
#3325000000
1"
0$
1!
#3330000000
0!
#3335000000
1$
1!
#3340000000
0!
#3345000000
1!
#3350000000
0!
#3355000000
1!
#3360000000
0!
#3365000000
0"
1!
#3370000000
0!
#3375000000
0$
1!
#3380000000
0!
#3385000000
1!
#3390000000
0!
#3395000000
1"
1!
#3400000000
0!
#3405000000
0"
1$
1!
#3410000000
0!
#3415000000
1"
0$
1!
#3420000000
0!
#3425000000
1$
1!
#3430000000
0!
#3435000000
1!
#3440000000
0!
#3445000000
1!
#3450000000
0!
#3455000000
0"
1!
#3460000000
0!
#3465000000
0$
1!
#3470000000
0!
#3475000000
1"
1!
#3480000000
0!
#3485000000
1$
1!
#3490000000
0!
#3495000000
1!
#3500000000
0!
#3505000000
0"
1!
#3510000000
0!
#3515000000
0$
1!
#3520000000
0!
#3525000000
1!
#3530000000
0!
#3535000000
1!
#3540000000
0!
#3545000000
1"
1!
#3550000000
0!
#3555000000
1$
1!
#3560000000
0!
#3565000000
1!
#3570000000
0!
#3575000000
1!
#3580000000
0!
#3585000000
1!
#3590000000
0!
#3595000000
0"
1!
#3600000000
0!
#3605000000
0$
1!
#3610000000
0!
#3615000000
1!
#3620000000
0!
#3625000000
1!
#3630000000
0!
#3635000000
1"
1!
#3640000000
0!
#3645000000
1$
1!
#3650000000
0!
#3655000000
1!
#3660000000
0!
#3665000000
1!
#3670000000
0!
#3675000000
0"
1!
#3680000000
0!
#3685000000
1"
0$
1!
#3690000000
0!
#3695000000
1$
1!
#3700000000
0!
#3705000000
0"
1!
#3710000000
0!
#3715000000
0$
1!
#3720000000
0!
#3725000000
1"
1!
#3730000000
0!
#3735000000
1$
1!
#3740000000
0!
#3745000000
0"
1!
#3750000000
0!
#3755000000
0$
1!
#3760000000
0!
#3765000000
1"
1!
#3770000000
0!
#3775000000
1$
1!
#3780000000
0!
#3785000000
1!
#3790000000
0!
#3795000000
1!
#3800000000
0!
#3805000000
1!
#3810000000
0!
#3815000000
0"
1!
#3820000000
0!
#3825000000
0$
1!
#3830000000
0!
#3835000000
1!
#3840000000
0!
#3845000000
1"
1!
#3850000000
0!
#3855000000
1$
1!
#3860000000
0!
#3865000000
1!
#3870000000
0!
#3875000000
1!
#3880000000
0!
#3885000000
1!
#3890000000
0!
#3895000000
0"
1!
#3900000000
0!
#3905000000
0$
1!
#3910000000
0!
#3915000000
1"
1!
#3920000000
0!
#3925000000
0"
1$
1!
#3930000000
0!
#3935000000
0$
1!
#3940000000
0!
#3945000000
1"
1!
#3950000000
0!
#3955000000
1$
1!
#3960000000
0!
#3965000000
1!
#3970000000
0!
#3975000000
1!
#3980000000
0!
#3985000000
0"
1!
#3990000000
0!
#3995000000
0$
1!
#4000000000
0!
#4005000000
1!
#4010000000
0!
#4015000000
1!
#4020000000
0!
#4025000000
1"
1!
#4030000000
0!
#4035000000
1$
1!
#4040000000
0!
#4045000000
0"
1!
#4050000000
0!
#4055000000
0$
1!
#4060000000
0!
#4065000000
1!
#4070000000
0!
#4075000000
1!
#4080000000
0!
#4085000000
1"
1!
#4090000000
0!
#4095000000
1$
1!
#4100000000
0!
#4105000000
0"
1!
#4110000000
0!
#4115000000
0$
1!
#4120000000
0!
#4125000000
1!
#4130000000
0!
#4135000000
1!
#4140000000
0!
#4145000000
1"
1!
#4150000000
0!
#4155000000
1$
1!
#4160000000
0!
#4165000000
1!
#4170000000
0!
#4175000000
0"
1!
#4180000000
0!
#4185000000
0$
1!
#4190000000
0!
#4195000000
1"
1!
#4200000000
0!
#4205000000
1$
1!
#4210000000
0!
#4215000000
1!
#4220000000
0!
#4225000000
1!
#4230000000
0!
#4235000000
1!
#4240000000
0!
#4245000000
0"
1!
#4250000000
0!
#4255000000
1"
0$
1!
#4260000000
0!
#4265000000
1$
1!
#4270000000
0!
#4275000000
1!
#4280000000
0!
#4285000000
0"
1!
#4290000000
0!
#4295000000
0$
1!
#4300000000
0!
#4305000000
1!
#4310000000
0!
#4315000000
1!
#4320000000
0!
#4325000000
1!
#4330000000
0!
#4335000000
1"
1!
#4340000000
0!
#4345000000
1$
1!
#4350000000
0!
#4355000000
1!
#4360000000
0!
#4365000000
1!
#4370000000
0!
#4375000000
0"
1!
#4380000000
0!
#4385000000
0$
1!
#4390000000
0!
#4395000000
1"
1!
#4400000000
0!
#4405000000
1$
1!
#4410000000
0!
#4415000000
1!
#4420000000
0!
#4425000000
1!
#4430000000
0!
#4435000000
0"
1!
#4440000000
0!
#4445000000
0$
1!
#4450000000
0!
#4455000000
1!
#4460000000
0!
#4465000000
1!
#4470000000
0!
#4475000000
1"
1!
#4480000000
0!
#4485000000
1$
1!
#4490000000
0!
#4495000000
1!
#4500000000
0!
#4505000000
0"
1!
#4510000000
0!
#4515000000
1"
0$
1!
#4520000000
0!
#4525000000
1$
1!
#4530000000
0!
#4535000000
1!
#4540000000
0!
#4545000000
1!
#4550000000
0!
#4555000000
1!
#4560000000
0!
#4565000000
0"
1!
#4570000000
0!
#4575000000
0$
1!
#4580000000
0!
#4585000000
1"
1!
#4590000000
0!
#4595000000
1$
1!
#4600000000
0!
#4605000000
0"
1!
#4610000000
0!
#4615000000
0$
1!
#4620000000
0!
#4625000000
1!
#4630000000
0!
#4635000000
1!
#4640000000
0!
#4645000000
1!
#4650000000
0!
#4655000000
1"
1!
#4660000000
0!
#4665000000
1$
1!
#4670000000
0!
#4675000000
1!
#4680000000
0!
#4685000000
1!
#4690000000
0!
#4695000000
1!
#4700000000
0!
#4705000000
0"
1!
#4710000000
0!
#4715000000
1"
0$
1!
#4720000000
0!
#4725000000
1$
1!
#4730000000
0!
#4735000000
1!
#4740000000
0!
#4745000000
1!
#4750000000
0!
#4755000000
0"
1!
#4760000000
0!
#4765000000
0$
1!
#4770000000
0!
#4775000000
1!
#4780000000
0!
#4785000000
1!
#4790000000
0!
#4795000000
1"
1!
#4800000000
0!
#4805000000
1$
1!
#4810000000
0!
#4815000000
0"
1!
#4820000000
0!
#4825000000
0$
1!
#4830000000
0!
#4835000000
1!
#4840000000
0!
#4845000000
1"
1!
#4850000000
0!
#4855000000
1$
1!
#4860000000
0!
#4865000000
1!
#4870000000
0!
#4875000000
1!
#4880000000
0!
#4885000000
1!
#4890000000
0!
#4895000000
0"
1!
#4900000000
0!
#4905000000
0$
1!
#4910000000
0!
#4915000000
1!
#4920000000
0!
#4925000000
1!
#4930000000
0!
#4935000000
1"
1!
#4940000000
0!
#4945000000
1$
1!
#4950000000
0!
#4955000000
1!
#4960000000
0!
#4965000000
1!
#4970000000
0!
#4975000000
0"
1!
#4980000000
0!
#4985000000
0$
1!
#4990000000
0!
#4995000000
1!
#5000000000
0!
#5005000000
1!
#5010000000
0!
#5015000000
1!
#5020000000
0!
#5025000000
1"
1!
#5030000000
0!
#5035000000
1$
1!
#5040000000
0!
#5045000000
1!
#5050000000
0!
#5055000000
1!
#5060000000
0!
#5065000000
0"
1!
#5070000000
0!
#5075000000
0$
1!
#5080000000
0!
#5085000000
1!
#5090000000
0!
#5095000000
1"
1!
#5100000000
0!
#5105000000
0"
1$
1!
#5110000000
0!
#5115000000
0$
1!
#5120000000
0!
#5125000000
1!
#5130000000
0!
#5135000000
1!
#5140000000
0!
#5145000000
1!
#5150000000
0!
#5155000000
1"
1!
#5160000000
0!
#5165000000
1$
1!
#5170000000
0!
#5175000000
0"
1!
#5180000000
0!
#5185000000
0$
1!
#5190000000
0!
#5195000000
1!
#5200000000
0!
#5205000000
1!
#5210000000
0!
#5215000000
1"
1!
#5220000000
0!
#5225000000
1$
1!
#5230000000
0!
#5235000000
1!
#5240000000
0!
#5245000000
0"
1!
#5250000000
0!
#5255000000
0$
1!
#5260000000
0!
#5265000000
1!
#5270000000
0!
#5275000000
1!
#5280000000
0!
#5285000000
1!
#5290000000
0!
#5295000000
1"
1!
#5300000000
0!
#5305000000
1$
1!
#5310000000
0!
#5315000000
1!
#5320000000
0!
#5325000000
0"
1!
#5330000000
0!
#5335000000
1"
0$
1!
#5340000000
0!
#5345000000
1$
1!
#5350000000
0!
#5355000000
1!
#5360000000
0!
#5365000000
0"
1!
#5370000000
0!
#5375000000
0$
1!
#5380000000
0!
#5385000000
1!
#5390000000
0!
#5395000000
1"
1!
#5400000000
0!
#5405000000
1$
1!
#5410000000
0!
#5415000000
1!
#5420000000
0!
#5425000000
1!
#5430000000
0!
#5435000000
0"
1!
#5440000000
0!
#5445000000
1"
0$
1!
#5450000000
0!
#5455000000
1$
1!
#5460000000
0!
#5465000000
1!
#5470000000
0!
#5475000000
1!
#5480000000
0!
#5485000000
1!
#5490000000
0!
#5495000000
0"
1!
#5500000000
0!
#5505000000
0$
1!
#5510000000
0!
#5515000000
1!
#5520000000
0!
#5525000000
1!
#5530000000
0!
#5535000000
1"
1!
#5540000000
0!
#5545000000
1$
1!
#5550000000
0!
#5555000000
0"
1!
#5560000000
0!
#5565000000
0$
1!
#5570000000
0!
#5575000000
1!
#5580000000
0!
#5585000000
1"
1!
#5590000000
0!
#5595000000
1$
1!
#5600000000
0!
#5605000000
1!
#5610000000
0!
#5615000000
0"
1!
#5620000000
0!
#5625000000
0$
1!
#5630000000
0!
#5635000000
1!
#5640000000
0!
#5645000000
1"
1!
#5650000000
0!
#5655000000
1$
1!
#5660000000
0!
#5665000000
1!
#5670000000
0!
#5675000000
0"
1!
#5680000000
0!
#5685000000
0$
1!
#5690000000
0!
#5695000000
1"
1!
#5700000000
0!
#5705000000
0"
1$
1!
#5710000000
0!
#5715000000
0$
1!
#5720000000
0!
#5725000000
1!
#5730000000
0!
#5735000000
1"
1!
#5740000000
0!
#5745000000
1$
1!
#5750000000
0!
#5755000000
1!
#5760000000
0!
#5765000000
1!
#5770000000
0!
#5775000000
1!
#5780000000
0!
#5785000000
0"
1!
#5790000000
0!
#5795000000
1"
0$
1!
#5800000000
0!
#5805000000
1$
1!
#5810000000
0!
#5815000000
1!
#5820000000
0!
#5825000000
0"
1!
#5830000000
0!
#5835000000
0$
1!
#5840000000
0!
#5845000000
1"
1!
#5850000000
0!
#5855000000
1$
1!
#5860000000
0!
#5865000000
1!
#5870000000
0!
#5875000000
1!
#5880000000
0!
#5885000000
1!
#5890000000
0!
#5895000000
0"
1!
#5900000000
0!
#5905000000
1"
0$
1!
#5910000000
0!
#5915000000
1$
1!
#5920000000
0!
#5925000000
1!
#5930000000
0!
#5935000000
1!
#5940000000
0!
#5945000000
1!
#5950000000
0!
#5955000000
0"
1!
#5960000000
0!
#5965000000
0$
1!
#5970000000
0!
#5975000000
1!
#5980000000
0!
#5985000000
1!
#5990000000
0!
#5995000000
1!
#6000000000
0!
#6005000000
1"
1!
#6010000000
0!
#6015000000
1$
1!
#6020000000
0!
#6025000000
0"
1!
#6030000000
0!
#6035000000
1"
0$
1!
#6040000000
0!
#6045000000
1$
1!
#6050000000
0!
#6055000000
0"
1!
#6060000000
0!
#6065000000
0$
1!
#6070000000
0!
#6075000000
1!
#6080000000
0!
#6085000000
1"
1!
#6090000000
0!
#6095000000
1$
1!
#6100000000
0!
#6105000000
1!
#6110000000
0!
#6115000000
0"
1!
#6120000000
0!
#6125000000
0$
1!
#6130000000
0!
#6135000000
1!
#6140000000
0!
#6145000000
1!
#6150000000
0!
#6155000000
1!
#6160000000
0!
#6165000000
1"
1!
#6170000000
0!
#6175000000
1$
1!
#6180000000
0!
#6185000000
0"
1!
#6190000000
0!
#6195000000
1"
0$
1!
#6200000000
0!
#6205000000
1$
1!
#6210000000
0!
#6215000000
0"
1!
#6220000000
0!
#6225000000
0$
1!
#6230000000
0!
#6235000000
1!
#6240000000
0!
#6245000000
1!
#6250000000
0!
#6255000000
1!
#6260000000
0!
#6265000000
1"
1!
#6270000000
0!
#6275000000
1$
1!
#6280000000
0!
#6285000000
0"
1!
#6290000000
0!
#6295000000
1"
0$
1!
#6300000000
0!
#6305000000
1$
1!
#6310000000
0!
#6315000000
1!
#6320000000
0!
#6325000000
1!
#6330000000
0!
#6335000000
1!
#6340000000
0!
#6345000000
0"
1!
#6350000000
0!
#6355000000
0$
1!
#6360000000
0!
#6365000000
1!
#6370000000
0!
#6375000000
1!
#6380000000
0!
#6385000000
1"
1!
#6390000000
0!
#6395000000
1$
1!
#6400000000
0!
#6405000000
1!
#6410000000
0!
#6415000000
1!
#6420000000
0!
#6425000000
0"
1!
#6430000000
0!
#6435000000
0$
1!
#6440000000
0!
#6445000000
1!
#6450000000
0!
#6455000000
1!
#6460000000
0!
#6465000000
1!
#6470000000
0!
#6475000000
1"
1!
#6480000000
0!
#6485000000
1$
1!
#6490000000
0!
#6495000000
0"
1!
#6500000000
0!
#6505000000
1"
0$
1!
#6510000000
0!
#6515000000
1$
1!
#6520000000
0!
#6525000000
1!
#6530000000
0!
#6535000000
1!
#6540000000
0!
#6545000000
1!
#6550000000
0!
#6555000000
0"
1!
#6560000000
0!
#6565000000
0$
1!
#6570000000
0!
#6575000000
1!
#6580000000
0!
#6585000000
1"
1!
#6590000000
0!
#6595000000
0"
1$
1!
#6600000000
0!
#6605000000
0$
1!
#6610000000
0!
#6615000000
1!
#6620000000
0!
#6625000000
1"
1!
#6630000000
0!
#6635000000
1$
1!
#6640000000
0!
#6645000000
1!
#6650000000
0!
#6655000000
1!
#6660000000
0!
#6665000000
0"
1!
#6670000000
0!
#6675000000
0$
1!
#6680000000
0!
#6685000000
1!
#6690000000
0!
#6695000000
1!
#6700000000
0!
#6705000000
1"
1!
#6710000000
0!
#6715000000
1$
1!
#6720000000
0!
#6725000000
1!
#6730000000
0!
#6735000000
1!
#6740000000
0!
#6745000000
1!
#6750000000
0!
#6755000000
0"
1!
#6760000000
0!
#6765000000
1"
0$
1!
#6770000000
0!
#6775000000
0"
1$
1!
#6780000000
0!
#6785000000
0$
1!
#6790000000
0!
#6795000000
1!
#6800000000
0!
#6805000000
1"
1!
#6810000000
0!
#6815000000
1$
1!
#6820000000
0!
#6825000000
1!
#6830000000
0!
#6835000000
0"
1!
#6840000000
0!
#6845000000
0$
1!
#6850000000
0!
#6855000000
1!
#6860000000
0!
#6865000000
1"
1!
#6870000000
0!
#6875000000
1$
1!
#6880000000
0!
#6885000000
1!
#6890000000
0!
#6895000000
0"
1!
#6900000000
0!
#6905000000
0$
1!
#6910000000
0!
#6915000000
1"
1!
#6920000000
0!
#6925000000
1$
1!
#6930000000
0!
#6935000000
1!
#6940000000
0!
#6945000000
1!
#6950000000
0!
#6955000000
0"
1!
#6960000000
0!
#6965000000
0$
1!
#6970000000
0!
#6975000000
1!
#6980000000
0!
#6985000000
1"
1!
#6990000000
0!
#6995000000
1$
1!
#7000000000
0!
#7005000000
0"
1!
#7010000000
0!
#7015000000
0$
1!
#7020000000
0!
#7025000000
1!
#7030000000
0!
#7035000000
1!
#7040000000
0!
#7045000000
1"
1!
#7050000000
0!
#7055000000
1$
1!
#7060000000
0!
#7065000000
1!
#7070000000
0!
#7075000000
0"
1!
#7080000000
0!
#7085000000
0$
1!
#7090000000
0!
#7095000000
1"
1!
#7100000000
0!
#7105000000
1$
1!
#7110000000
0!
#7115000000
1!
#7120000000
0!
#7125000000
0"
1!
#7130000000
0!
#7135000000
1"
0$
1!
#7140000000
0!
#7145000000
0"
1$
1!
#7150000000
0!
#7155000000
0$
1!
#7160000000
0!
#7165000000
1!
#7170000000
0!
#7175000000
1!
#7180000000
0!
